poetry_plugin_commands/__init__.py
poetry_plugin_commands/command.py
poetry_plugin_commands/plugins.py
poetry_plugin_commands-0.0.9.dist-info/LICENSE
poetry_plugin_commands-0.0.9.dist-info/METADATA
poetry_plugin_commands-0.0.9.dist-info/WHEEL
poetry_plugin_commands-0.0.9.dist-info/entry_points.txt
poetry_plugin_commands-0.0.9.dist-info/RECORD
